Workbook

Sheet 功能清单（新架构）
A1: 序号 | B1: 一级模块 | C1: 二级功能 | D1: 功能说明 | E1: 冠麦对应功能 | F1: 处置 | G1: 优先级 | H1: 所属版本 | I1: 备注/关联
A2: 1 | B2: 1 工作台 | C2: 待办聚合带 | D2: 跨模块待办汇总，点击直达处理页 | E2: — | F2: 新增 | G2: P0 | H2: =IF($G2="P0","一期",IF($G2="P1","二期",IF($G2="P2","三期",IF($G2="并行","并行推进",IF($G2="待拍板","待定","不开发"))))) -> 一期
A3: 2 | B3: 1 工作台 | C3: 业务地图导航 | D3: 四层架构图即菜单：流动箭头、当前环节提示、待办角标 | E3: — | F3: 新增 | G3: P0 | H3: =IF($G3="P0","一期",IF($G3="P1","二期",IF($G3="P2","三期",IF($G3="并行","并行推进",IF($G3="待拍板","待定","不开发"))))) -> 一期 | I3: 首页形态随Q8
A4: 3 | B4: 1 工作台 | C4: 流程演示动画 | D4: 分步点亮四层与主线，培训与展厅通用 | E4: — | F4: 新增 | G4: P0 | H4: =IF($G4="P0","一期",IF($G4="P1","二期",IF($G4="P2","三期",IF($G4="并行","并行推进",IF($G4="待拍板","待定","不开发"))))) -> 一期
A5: 4 | B5: 1 工作台 | C5: 功能搜索直达 | D5: 按功能名搜索直达并高亮 | E5: — | F5: 新增 | G5: P0 | H5: =IF($G5="P0","一期",IF($G5="P1","二期",IF($G5="P2","三期",IF($G5="并行","并行推进",IF($G5="待拍板","待定","不开发"))))) -> 一期
A6: 5 | B6: 1 工作台 | C6: 新手引导 | D6: 聚光灯分步引导，可重播 | E6: — | F6: 新增 | G6: P0 | H6: =IF($G6="P0","一期",IF($G6="P1","二期",IF($G6="P2","三期",IF($G6="并行","并行推进",IF($G6="待拍板","待定","不开发"))))) -> 一期
A7: 6 | B7: 1 工作台 | C7: 消息通知 | D7: 审批与异常提醒 | E7: — | F7: 新增 | G7: P1 | H7: =IF($G7="P0","一期",IF($G7="P1","二期",IF($G7="P2","三期",IF($G7="并行","并行推进",IF($G7="待拍板","待定","不开发"))))) -> 二期
A8: 7 | B8: 2 基础档案 | C8: 企业信息/资质/配置 | D8: 企业基本资料与资质证照 | E8: 截图未提供（待补对照） | F8: 新增 | G8: P0 | H8: =IF($G8="P0","一期",IF($G8="P1","二期",IF($G8="P2","三期",IF($G8="并行","并行推进",IF($G8="待拍板","待定","不开发"))))) -> 一期 | I8: 冠麦系统设置板块未截图
A9: 8 | B9: 2 基础档案 | C9: 组织管理 | D9: 企业/门店/工厂/车间/生产线；产线自建供生产计划引用 | E9: 工厂模型（生产设置） | F9: 移位归并 | G9: P0 | H9: =IF($G9="P0","一期",IF($G9="P1","二期",IF($G9="P2","三期",IF($G9="并行","并行推进",IF($G9="待拍板","待定","不开发"))))) -> 一期
A10: 9 | B10: 2 基础档案 | C10: 员工档案 | D10: 员工基础信息；采购员并入（角色标识） | E10: 采购员（采购管理） | F10: 移位归并 | G10: P0 | H10: =IF($G10="P0","一期",IF($G10="P1","二期",IF($G10="P2","三期",IF($G10="并行","并行推进",IF($G10="待拍板","待定","不开发"))))) -> 一期
A11: 10 | B11: 2 基础档案 | C11: 账号/角色/审批权限 | D11: 账号开通、角色授权、审批权限 | E11: 截图未提供（待补对照） | F11: 新增 | G11: P0 | H11: =IF($G11="P0","一期",IF($G11="P1","二期",IF($G11="P2","三期",IF($G11="并行","并行推进",IF($G11="待拍板","待定","不开发"))))) -> 一期 | I11: 权限层级随Q6
A12: 11 | B12: 2 基础档案 | C12: 数据权限 | D12: 按组织/角色控制数据可见范围 | E12: 截图未提供 | F12: 新增 | G12: P1 | H12: =IF($G12="P0","一期",IF($G12="P1","二期",IF($G12="P2","三期",IF($G12="并行","并行推进",IF($G12="待拍板","待定","不开发"))))) -> 二期
A13: 12 | B13: 2 基础档案 | C13: 供应商档案 | D13: 供应商主数据与结算方式；采购只选用不修改 | E13: 供应商信息（采购-供应商管理） | F13: 移位归并 | G13: P0 | H13: =IF($G13="P0","一期",IF($G13="P1","二期",IF($G13="P2","三期",IF($G13="并行","并行推进",IF($G13="待拍板","待定","不开发"))))) -> 一期
A14: 13 | B14: 2 基础档案 | C14: 单据编号规则 | D14: 各类单据编号规则配置 | E14: 截图未提供 | F14: 新增 | G14: P0 | H14: =IF($G14="P0","一期",IF($G14="P1","二期",IF($G14="P2","三期",IF($G14="并行","并行推进",IF($G14="待拍板","待定","不开发"))))) -> 一期 | I14: 规则随Q5
A15: 14 | B15: 2 基础档案 | C15: 打印模板 | D15: 单据打印模板维护 | E15: 打印箱签为其一类（生产工具） | F15: 沿用 | G15: P0 | H15: =IF($G15="P0","一期",IF($G15="P1","二期",IF($G15="P2","三期",IF($G15="并行","并行推进",IF($G15="待拍板","待定","不开发"))))) -> 一期
A16: 15 | B16: 2 基础档案 | C16: 基础数据字典 | D16: 单位/类别等字典 | E16: 截图未提供 | F16: 新增 | G16: P0 | H16: =IF($G16="P0","一期",IF($G16="P1","二期",IF($G16="P2","三期",IF($G16="并行","并行推进",IF($G16="待拍板","待定","不开发"))))) -> 一期
A17: 16 | B17: 2 基础档案 | C17: 期初初始化 | D17: 商品池/BOM/客户/供应商/期初库存导入与校验 | E17: 截图未提供 | F17: 新增 | G17: P0 | H17: =IF($G17="P0","一期",IF($G17="P1","二期",IF($G17="P2","三期",IF($G17="并行","并行推进",IF($G17="待拍板","待定","不开发"))))) -> 一期
A18: 17 | B18: 2 基础档案 | C18: 审批流配置 | D18: 订单/对账/结款审批链 | E18: 截图未提供 | F18: 新增 | G18: P1 | H18: =IF($G18="P0","一期",IF($G18="P1","二期",IF($G18="P2","三期",IF($G18="并行","并行推进",IF($G18="待拍板","待定","不开发"))))) -> 二期
A19: 18 | B19: 3 商品/BOM | C19: 商品分类 | D19: 分类树维护 | E19: 商品分类（商品设置） | F19: 沿用 | G19: P0 | H19: =IF($G19="P0","一期",IF($G19="P1","二期",IF($G19="P2","三期",IF($G19="并行","并行推进",IF($G19="待拍板","待定","不开发"))))) -> 一期
A20: 19 | B20: 3 商品/BOM | C20: 商品单位 | D20: 计量单位维护 | E20: 商品列表内字段 | F20: 沿用 | G20: P0 | H20: =IF($G20="P0","一期",IF($G20="P1","二期",IF($G20="P2","三期",IF($G20="并行","并行推进",IF($G20="待拍板","待定","不开发"))))) -> 一期
A21: 20 | B21: 3 商品/BOM | C21: 商品税率 | D21: 税率维护（会议明确保留） | E21: 商品税率（商品设置） | F21: 沿用 | G21: P0 | H21: =IF($G21="P0","一期",IF($G21="P1","二期",IF($G21="P2","三期",IF($G21="并行","并行推进",IF($G21="待拍板","待定","不开发"))))) -> 一期
A22: 21 | B22: 3 商品/BOM | C22: 商品标签 | D22: 商品维度标签 | E22: — | F22: 新增 | G22: P1 | H22: =IF($G22="P0","一期",IF($G22="P1","二期",IF($G22="P2","三期",IF($G22="并行","并行推进",IF($G22="待拍板","待定","不开发"))))) -> 二期 | I22: 随Q10
A23: 22 | B23: 3 商品/BOM | C23: 商品档案（统一商品池） | D23: 原料/半成品/加工品/成品同池，分类筛选 | E23: 商品列表（商品管理） | F23: 沿用 | G23: P0 | H23: =IF($G23="P0","一期",IF($G23="P1","二期",IF($G23="P2","三期",IF($G23="并行","并行推进",IF($G23="待拍板","待定","不开发"))))) -> 一期
A24: 23 | B24: 3 商品/BOM | C24: 商品编码 | D24: 全局唯一（硬约束） | E24: 商品列表内 | F24: 沿用 | G24: P0 | H24: =IF($G24="P0","一期",IF($G24="P1","二期",IF($G24="P2","三期",IF($G24="并行","并行推进",IF($G24="待拍板","待定","不开发"))))) -> 一期
A25: 24 | B25: 3 商品/BOM | C25: 组合商品 | D25: 套餐类组合，对应BZ组合单 | E25: 组合商品（商品管理） | F25: 沿用 | G25: P0 | H25: =IF($G25="P0","一期",IF($G25="P1","二期",IF($G25="P2","三期",IF($G25="并行","并行推进",IF($G25="待拍板","待定","不开发"))))) -> 一期
A26: 25 | B26: 3 商品/BOM | C26: 生产BOM维护 | D26: 三级BOM＋出成率/损耗率，物料需求按其展开 | E26: 生产BOM管理（生产-BOM管理） | F26: 移位归并 | G26: P0 | H26: =IF($G26="P0","一期",IF($G26="P1","二期",IF($G26="P2","三期",IF($G26="并行","并行推进",IF($G26="待拍板","待定","不开发"))))) -> 一期 | I26: BOM归商品域
A27: 26 | B27: 3 商品/BOM | C27: 研发BOM | D27: 研发配方独立管理 | E27: 研发BOM管理（生产-BOM管理） | F27: 待确认 | G27: 待拍板 | H27: =IF($G27="P0","一期",IF($G27="P1","二期",IF($G27="P2","三期",IF($G27="并行","并行推进",IF($G27="待拍板","待定","不开发"))))) -> 待定 | I27: 会议未提；MVP建议先生产BOM
A28: 27 | B28: 3 商品/BOM | C28: 商品内标管理 | D28: 商品内部标识/条码 | E28: 商品内标管理（生产设置） | F28: 待确认 | G28: 待拍板 | H28: =IF($G28="P0","一期",IF($G28="P1","二期",IF($G28="P2","三期",IF($G28="并行","并行推进",IF($G28="待拍板","待定","不开发"))))) -> 待定 | I28: 会议未提
A29: 28 | B29: 3 商品/BOM | C29: 临时商品审批 | D29: — | E29: 临时商品审批（商品管理） | F29: 裁剪 | G29: 裁剪 | H29: =IF($G29="P0","一期",IF($G29="P1","二期",IF($G29="P2","三期",IF($G29="并行","并行推进",IF($G29="待拍板","待定","不开发"))))) -> 不开发 | I29: 07-06会议
A30: 29 | B30: 3 商品/BOM | C30: 替代商品（物料替换） | D30: — | E30: 替代商品（生产设置） | F30: 裁剪 | G30: 裁剪 | H30: =IF($G30="P0","一期",IF($G30="P1","二期",IF($G30="P2","三期",IF($G30="并行","并行推进",IF($G30="待拍板","待定","不开发"))))) -> 不开发 | I30: 07-06会议
A31: 30 | B31: 3 商品/BOM | C31: 价格管理体系 | D31: 客户报价单/协议价/历史报价整套 | E31: 客户报价单/客户协议价/历史报价（价格管理） | F31: 裁剪 | G31: 裁剪 | H31: =IF($G31="P0","一期",IF($G31="P1","二期",IF($G31="P2","三期",IF($G31="并行","并行推进",IF($G31="待拍板","待定","不开发"))))) -> 不开发 | I31: 07-06会议
A32: 31 | B32: 4 订单中心 | C32: 订单录入/导入 | D32: 手工录单＋Excel导入 | E32: 订单列表（新建/导入） | F32: 沿用 | G32: P0 | H32: =IF($G32="P0","一期",IF($G32="P1","二期",IF($G32="P2","三期",IF($G32="并行","并行推进",IF($G32="待拍板","待定","不开发"))))) -> 一期
A33: 32 | B33: 4 订单中心 | C33: 订单列表 | D33: 全部订单查询跟踪 | E33: 订单列表 | F33: 沿用 | G33: P0 | H33: =IF($G33="P0","一期",IF($G33="P1","二期",IF($G33="P2","三期",IF($G33="并行","并行推进",IF($G33="待拍板","待定","不开发"))))) -> 一期
A34: 33 | B34: 4 订单中心 | C34: 订单审核 | D34: 通过方可参与汇总，留痕 | E34: 订单审核 | F34: 沿用 | G34: P0 | H34: =IF($G34="P0","一期",IF($G34="P1","二期",IF($G34="P2","三期",IF($G34="并行","并行推进",IF($G34="待拍板","待定","不开发"))))) -> 一期
A35: 34 | B35: 4 订单中心 | C35: 订单汇总→转生产需求 | D35: 按交期汇总，一键转生产 | E35: （冠麦为生产计划内订单纳入） | F35: 沿用 | G35: P0 | H35: =IF($G35="P0","一期",IF($G35="P1","二期",IF($G35="P2","三期",IF($G35="并行","并行推进",IF($G35="待拍板","待定","不开发"))))) -> 一期 | I35: 汇总口径随决议
A36: 35 | B36: 4 订单中心 | C36: 订单分解 | D36: 按客户维度分解，与分拣投框联动 | E36: （由分拣进度/明细承接） | F36: 沿用 | G36: P1 | H36: =IF($G36="P0","一期",IF($G36="P1","二期",IF($G36="P2","三期",IF($G36="并行","并行推进",IF($G36="待拍板","待定","不开发"))))) -> 二期 | I36: 分解逻辑核对中
A37: 36 | B37: 4 订单中心 | C37: 订单对账→转财务 | D37: 对账审批通过流转财务结算 | E37: 对账审批 | F37: 沿用 | G37: P0 | H37: =IF($G37="P0","一期",IF($G37="P1","二期",IF($G37="P2","三期",IF($G37="并行","并行推进",IF($G37="待拍板","待定","不开发"))))) -> 一期
A38: 37 | B38: 4 订单中心 | C38: 订单变更 | D38: 已审订单变更与影响提示 | E38: 订单列表内操作 | F38: 沿用 | G38: P1 | H38: =IF($G38="P0","一期",IF($G38="P1","二期",IF($G38="P2","三期",IF($G38="并行","并行推进",IF($G38="待拍板","待定","不开发"))))) -> 二期
A39: 38 | B39: 4 订单中心 | C39: 预订单 | D39: 净配菜次日生产核心单据 | E39: 预订单 | F39: 待确认 | G39: 待拍板 | H39: =IF($G39="P0","一期",IF($G39="P1","二期",IF($G39="P2","三期",IF($G39="并行","并行推进",IF($G39="待拍板","待定","不开发"))))) -> 待定 | I39: Q1
A40: 39 | B40: 4 订单中心 | C40: 套账数据 | D40: 订单套账口径 | E40: 套账数据 | F40: 待确认 | G40: 待拍板 | H40: =IF($G40="P0","一期",IF($G40="P1","二期",IF($G40="P2","三期",IF($G40="并行","并行推进",IF($G40="待拍板","待定","不开发"))))) -> 待定 | I40: Q7 口径待明确
A41: 40 | B41: 4 订单中心 | C41: 售后列表 | D41: 售后处理入口 | E41: 售后列表（售后） | F41: 延后 | G41: P2 | H41: =IF($G41="P0","一期",IF($G41="P1","二期",IF($G41="P2","三期",IF($G41="并行","并行推进",IF($G41="待拍板","待定","不开发"))))) -> 三期 | I41: 会议：暂时搁置后做
A42: 41 | B42: 4 订单中心 | C42: 菜谱下单 | D42: — | E42: 菜谱下单 | F42: 裁剪 | G42: 裁剪 | H42: =IF($G42="P0","一期",IF($G42="P1","二期",IF($G42="P2","三期",IF($G42="并行","并行推进",IF($G42="待拍板","待定","不开发"))))) -> 不开发
A43: 42 | B43: 4 订单中心 | C43: 未下单客户提醒 | D43: — | E43: 未下单客户 | F43: 裁剪 | G43: 裁剪 | H43: =IF($G43="P0","一期",IF($G43="P1","二期",IF($G43="P2","三期",IF($G43="并行","并行推进",IF($G43="待拍板","待定","不开发"))))) -> 不开发
A44: 43 | B44: 4 订单中心 | C44: 客户子账号/邀请码/订单标签 | D44: — | E44: 截图未见（客户板块未提供） | F44: 裁剪 | G44: 裁剪 | H44: =IF($G44="P0","一期",IF($G44="P1","二期",IF($G44="P2","三期",IF($G44="并行","并行推进",IF($G44="待拍板","待定","不开发"))))) -> 不开发 | I44: 07-06会议
A45: 44 | B45: 5 采购中心 | C45: 采购需求 | D45: 由生产物料缺口生成或手工提出 | E45: — | F45: 新增 | G45: P1 | H45: =IF($G45="P0","一期",IF($G45="P1","二期",IF($G45="P2","三期",IF($G45="并行","并行推进",IF($G45="待拍板","待定","不开发"))))) -> 二期
A46: 45 | B46: 5 采购中心 | C46: 统一采购单 | D46: 采购计划＋补采＋采购单据三合一；支持后补录入 | E46: 采购计划/补采/采购单据（采购管理） | F46: 合并整合 | G46: P1 | H46: =IF($G46="P0","一期",IF($G46="P1","二期",IF($G46="P2","三期",IF($G46="并行","并行推进",IF($G46="待拍板","待定","不开发"))))) -> 二期 | I46: 07-06会议：三合一
A47: 46 | B47: 5 采购中心 | C47: 代采单 | D47: 代客采购单据 | E47: 代采单（采购管理） | F47: 待确认 | G47: 待拍板 | H47: =IF($G47="P0","一期",IF($G47="P1","二期",IF($G47="P2","三期",IF($G47="并行","并行推进",IF($G47="待拍板","待定","不开发"))))) -> 待定 | I47: 会议未提；建议并入统一采购单或裁剪
A48: 47 | B48: 5 采购中心 | C48: 到货登记/采购验收 | D48: 到货与验收差异留痕 | E48: 采购单据流程内 | F48: 沿用 | G48: P1 | H48: =IF($G48="P0","一期",IF($G48="P1","二期",IF($G48="P2","三期",IF($G48="并行","并行推进",IF($G48="待拍板","待定","不开发"))))) -> 二期
A49: 48 | B49: 5 采购中心 | C49: 检测报告 | D49: 供应商报告随单上传，联动质检溯源 | E49: 检测报告（采购-质检管理） | F49: 沿用 | G49: P1 | H49: =IF($G49="P0","一期",IF($G49="P1","二期",IF($G49="P2","三期",IF($G49="并行","并行推进",IF($G49="待拍板","待定","不开发"))))) -> 二期
A50: 49 | B50: 5 采购中心 | C50: 结款审批 | D50: 审批后转财务供应商结算 | E50: 结款审批 | F50: 沿用 | G50: P1 | H50: =IF($G50="P0","一期",IF($G50="P1","二期",IF($G50="P2","三期",IF($G50="并行","并行推进",IF($G50="待拍板","待定","不开发"))))) -> 二期
A51: 50 | B51: 5 采购中心 | C51: 采购规则/供货比例 | D51: — | E51: 采购计划规则/供货比例（采购规则） | F51: 裁剪 | G51: 裁剪 | H51: =IF($G51="P0","一期",IF($G51="P1","二期",IF($G51="P2","三期",IF($G51="并行","并行推进",IF($G51="待拍板","待定","不开发"))))) -> 不开发 | I51: 07-06会议
A52: 51 | B52: 5 采购中心 | C52: 询价记录/询价单/采购协议价 | D52: — | E52: 询价记录/询价单/采购协议价 | F52: 裁剪 | G52: 裁剪 | H52: =IF($G52="P0","一期",IF($G52="P1","二期",IF($G52="P2","三期",IF($G52="并行","并行推进",IF($G52="待拍板","待定","不开发"))))) -> 不开发 | I52: 07-06会议
A53: 52 | B53: 6 库存中心 | C53: 出入库管理-入库单 | D53: 采购入库/生产入库/其他入库合并为入库单 | E53: 采购入库单/其他入库单（入库管理） | F53: 合并整合 | G53: P1 | H53: =IF($G53="P0","一期",IF($G53="P1","二期",IF($G53="P2","三期",IF($G53="并行","并行推进",IF($G53="待拍板","待定","不开发"))))) -> 二期
A54: 53 | B54: 6 库存中心 | C54: 出入库管理-出库单 | D54: 销售出库/领料出库/其他出库合并为出库单 | E54: 销售出库单/其他出库单（出库管理） | F54: 合并整合 | G54: P1 | H54: =IF($G54="P0","一期",IF($G54="P1","二期",IF($G54="P2","三期",IF($G54="并行","并行推进",IF($G54="待拍板","待定","不开发"))))) -> 二期
A55: 54 | B55: 6 库存中心 | C55: 退货类单据 | D55: 销售退货入库/采购退货出库/其他退货 | E55: 销售退货入库单/采购退货出库单等4类 | F55: 待确认 | G55: 待拍板 | H55: =IF($G55="P0","一期",IF($G55="P1","二期",IF($G55="P2","三期",IF($G55="并行","并行推进",IF($G55="待拍板","待定","不开发"))))) -> 待定 | I55: 会议未提；建议销售退货随售后延后、采购退货P1
A56: 55 | B56: 6 库存中心 | C56: 库存盘点 | D56: 盘点任务＋盘盈入库＋盘亏出库合并 | E56: 盘点任务/盘盈单入库单/盘亏单出库单 | F56: 合并整合 | G56: P1 | H56: =IF($G56="P0","一期",IF($G56="P1","二期",IF($G56="P2","三期",IF($G56="并行","并行推进",IF($G56="待拍板","待定","不开发"))))) -> 二期
A57: 56 | B57: 6 库存中心 | C57: 组装拆卸单 | D57: 组合商品组装/拆卸出入库 | E57: 组装拆卸单（盘点管理） | F57: 待确认 | G57: 待拍板 | H57: =IF($G57="P0","一期",IF($G57="P1","二期",IF($G57="P2","三期",IF($G57="并行","并行推进",IF($G57="待拍板","待定","不开发"))))) -> 待定 | I57: 会议未提；与组合商品联动
A58: 57 | B58: 6 库存中心 | C58: 库存查询 | D58: 现存量与出入库明细查询 | E58: 库存查询表/出入库明细（库存数据） | F58: 沿用 | G58: P1 | H58: =IF($G58="P0","一期",IF($G58="P1","二期",IF($G58="P2","三期",IF($G58="并行","并行推进",IF($G58="待拍板","待定","不开发"))))) -> 二期
A59: 58 | B59: 6 库存中心 | C59: 库存预警 | D59: 低于安全库存提醒 | E59: — | F59: 新增 | G59: P2 | H59: =IF($G59="P0","一期",IF($G59="P1","二期",IF($G59="P2","三期",IF($G59="并行","并行推进",IF($G59="待拍板","待定","不开发"))))) -> 三期
A60: 59 | B60: 6 库存中心 | C60: 批次/保质期管理 | D60: 食品安全相关 | E60: 截图未见明确入口 | F60: 新增 | G60: P2 | H60: =IF($G60="P0","一期",IF($G60="P1","二期",IF($G60="P2","三期",IF($G60="并行","并行推进",IF($G60="待拍板","待定","不开发"))))) -> 三期 | I60: 随Q9
A61: 60 | B61: 6 库存中心 | C61: 库存成本 | D61: 成本调整单与成本核算 | E61: 成本调整单/成本核算（成本管理） | F61: 待确认 | G61: 待拍板 | H61: =IF($G61="P0","一期",IF($G61="P1","二期",IF($G61="P2","三期",IF($G61="并行","并行推进",IF($G61="待拍板","待定","不开发"))))) -> 待定 | I61: 归属随Q4
A62: 61 | B62: 6 库存中心 | C62: 调拨管理 | D62: — | E62: 调拨任务/调拨出库单/调拨入库单 | F62: 裁剪 | G62: 裁剪 | H62: =IF($G62="P0","一期",IF($G62="P1","二期",IF($G62="P2","三期",IF($G62="并行","并行推进",IF($G62="待拍板","待定","不开发"))))) -> 不开发 | I62: 07-06会议
A63: 62 | B63: 6 库存中心 | C63: 仓位类（上下架/移库） | D63: — | E63: 上下架管理/移库单 | F63: 裁剪 | G63: 裁剪 | H63: =IF($G63="P0","一期",IF($G63="P1","二期",IF($G63="P2","三期",IF($G63="并行","并行推进",IF($G63="待拍板","待定","不开发"))))) -> 不开发 | I63: 07-06会议：仓位管理裁剪
A64: 63 | B64: 6 库存中心 | C64: 在途库存分布 | D64: — | E64: 在途库存分布（库存数据） | F64: 裁剪 | G64: 裁剪 | H64: =IF($G64="P0","一期",IF($G64="P1","二期",IF($G64="P2","三期",IF($G64="并行","并行推进",IF($G64="待拍板","待定","不开发"))))) -> 不开发 | I64: 07-06会议
A65: 64 | B65: 6 库存中心 | C65: 占用/待出库分布 | D65: 库存占用与待出库视图 | E65: 占用库存分布/待出库数据分布 | F65: 延后 | G65: P2 | H65: =IF($G65="P0","一期",IF($G65="P1","二期",IF($G65="P2","三期",IF($G65="并行","并行推进",IF($G65="待拍板","待定","不开发"))))) -> 三期 | I65: 会议未提，建议延后
A66: 65 | B66: 7 生产中心 | C66: 生产计划 | D66: 按交期＋产线新建；无餐次字段 | E66: 生产计划（生产管理） | F66: 沿用 | G66: P0 | H66: =IF($G66="P0","一期",IF($G66="P1","二期",IF($G66="P2","三期",IF($G66="并行","并行推进",IF($G66="待拍板","待定","不开发"))))) -> 一期
A67: 66 | B67: 7 生产中心 | C67: 生产需求（订单纳入） | D67: 汇总转入＋手动补录；SC/BZ单 | E67: 生产计划内订单纳入 | F67: 沿用 | G67: P0 | H67: =IF($G67="P0","一期",IF($G67="P1","二期",IF($G67="P2","三期",IF($G67="并行","并行推进",IF($G67="待拍板","待定","不开发"))))) -> 一期 | I67: 编号随Q5
A68: 67 | B68: 7 生产中心 | C68: 物料需求（BOM展开） | D68: 毛料＝净料÷出成率，缺口提示 | E68: 领料管理内原料明细 | F68: 沿用 | G68: P0 | H68: =IF($G68="P0","一期",IF($G68="P1","二期",IF($G68="P2","三期",IF($G68="并行","并行推进",IF($G68="待拍板","待定","不开发"))))) -> 一期
A69: 68 | B69: 7 生产中心 | C69: 领料管理 | D69: 生成领料单（LL）交仓库 | E69: 领料管理＋领料出库单（库存-生产） | F69: 沿用 | G69: P0 | H69: =IF($G69="P0","一期",IF($G69="P1","二期",IF($G69="P2","三期",IF($G69="并行","并行推进",IF($G69="待拍板","待定","不开发"))))) -> 一期
A70: 69 | B70: 7 生产中心 | C70: 下达工单 | D70: 需求转工单（RW）进入工序流转 | E70: 生产任务下达 | F70: 沿用 | G70: P0 | H70: =IF($G70="P0","一期",IF($G70="P1","二期",IF($G70="P2","三期",IF($G70="并行","并行推进",IF($G70="待拍板","待定","不开发"))))) -> 一期
A71: 70 | B71: 7 生产中心 | C71: 工序管理 | D71: 路线按品类维护；SC四道/BZ三道 | E71: 工序管理（生产设置） | F71: 沿用 | G71: P0 | H71: =IF($G71="P0","一期",IF($G71="P1","二期",IF($G71="P2","三期",IF($G71="并行","并行推进",IF($G71="待拍板","待定","不开发"))))) -> 一期
A72: 71 | B72: 7 生产中心 | C72: 工序报工 | D72: 开工→报工双动作留痕：时间/数量/损耗/报工人 | E72: 生产进度 | F72: 沿用 | G72: P0 | H72: =IF($G72="P0","一期",IF($G72="P1","二期",IF($G72="P2","三期",IF($G72="并行","并行推进",IF($G72="待拍板","待定","不开发"))))) -> 一期 | I72: 冠麦仅进度，新架构增强留痕；分批随Q3
A73: 72 | B73: 7 生产中心 | C73: 投料登记 | D73: 实际投料与标准BOM对照 | E73: 投料与产出记录 | F73: 沿用 | G73: P0 | H73: =IF($G73="P0","一期",IF($G73="P1","二期",IF($G73="P2","三期",IF($G73="并行","并行推进",IF($G73="待拍板","待定","不开发"))))) -> 一期
A74: 73 | B74: 7 生产中心 | C74: 产出登记 | D74: 末道工序开工后登记；回写进度并生成入库单 | E74: 产出管理＋生产入库单 | F74: 沿用 | G74: P0 | H74: =IF($G74="P0","一期",IF($G74="P1","二期",IF($G74="P2","三期",IF($G74="并行","并行推进",IF($G74="待拍板","待定","不开发"))))) -> 一期 | I74: 超产随Q2
A75: 74 | B75: 7 生产中心 | C75: 退料管理 | D75: 投料多退少补，退料入库 | E75: 退料管理＋退料入库单 | F75: 待确认 | G75: 待拍板 | H75: =IF($G75="P0","一期",IF($G75="P1","二期",IF($G75="P2","三期",IF($G75="并行","并行推进",IF($G75="待拍板","待定","不开发"))))) -> 待定 | I75: 会议未提；建议P1
A76: 75 | B76: 7 生产中心 | C76: 生产完工/完工结案 | D76: 全部产出后结案归档 | E76: （冠麦按进度100%） | F76: 新增 | G76: P0 | H76: =IF($G76="P0","一期",IF($G76="P1","二期",IF($G76="P2","三期",IF($G76="并行","并行推进",IF($G76="待拍板","待定","不开发"))))) -> 一期
A77: 76 | B77: 7 生产中心 | C77: 线边仓库存总览 | D77: 车间线边库存只读视图 | E77: 线边仓库存总览 | F77: 沿用 | G77: P1 | H77: =IF($G77="P0","一期",IF($G77="P1","二期",IF($G77="P2","三期",IF($G77="并行","并行推进",IF($G77="待拍板","待定","不开发"))))) -> 二期
A78: 77 | B78: 7 生产中心 | C78: 打印箱签 | D78: 产出箱签打印 | E78: 打印箱签（生产工具） | F78: 待确认 | G78: 待拍板 | H78: =IF($G78="P0","一期",IF($G78="P1","二期",IF($G78="P2","三期",IF($G78="并行","并行推进",IF($G78="待拍板","待定","不开发"))))) -> 待定 | I78: 会议未提；工厂实操建议P1保留
A79: 78 | B79: 7 生产中心 | C79: 生产线排程 | D79: 多产线任务排程 | E79: 工厂模型延伸 | F79: 沿用 | G79: P1 | H79: =IF($G79="P0","一期",IF($G79="P1","二期",IF($G79="P2","三期",IF($G79="并行","并行推进",IF($G79="待拍板","待定","不开发"))))) -> 二期
A80: 79 | B80: 7 生产中心 | C80: 损耗记录汇总 | D80: 工序与产出损耗汇总 | E80: 投料产出记录内 | F80: 沿用 | G80: P1 | H80: =IF($G80="P0","一期",IF($G80="P1","二期",IF($G80="P2","三期",IF($G80="并行","并行推进",IF($G80="待拍板","待定","不开发"))))) -> 二期
A81: 80 | B81: 7 生产中心 | C81: 商品台账 | D81: 生产商品台账 | E81: 商品台账（生产管理） | F81: 延后 | G81: P2 | H81: =IF($G81="P0","一期",IF($G81="P1","二期",IF($G81="P2","三期",IF($G81="并行","并行推进",IF($G81="待拍板","待定","不开发"))))) -> 三期 | I81: 归报表中心
A82: 81 | B82: 7 生产中心 | C82: 餐次管理 | D82: — | E82: 生产计划内餐次 | F82: 裁剪 | G82: 裁剪 | H82: =IF($G82="P0","一期",IF($G82="P1","二期",IF($G82="P2","三期",IF($G82="并行","并行推进",IF($G82="待拍板","待定","不开发"))))) -> 不开发 | I82: 07-06会议
A83: 82 | B83: 7 生产中心 | C83: 净菜菜谱管理 | D83: — | E83: 菜谱相关 | F83: 裁剪 | G83: 裁剪 | H83: =IF($G83="P0","一期",IF($G83="P1","二期",IF($G83="P2","三期",IF($G83="并行","并行推进",IF($G83="待拍板","待定","不开发"))))) -> 不开发 | I83: 07-06会议
A84: 83 | B84: 7 生产中心 | C84: 猪肉分割类生产 | D84: — | E84: — | F84: 裁剪 | G84: 裁剪 | H84: =IF($G84="P0","一期",IF($G84="P1","二期",IF($G84="P2","三期",IF($G84="并行","并行推进",IF($G84="待拍板","待定","不开发"))))) -> 不开发 | I84: 07-06会议
A85: 84 | B85: 8 质检溯源 | C85: 质检管理（执行） | D85: 质检任务与结果记录 | E85: 质检管理 | F85: 沿用 | G85: P1 | H85: =IF($G85="P0","一期",IF($G85="P1","二期",IF($G85="P2","三期",IF($G85="并行","并行推进",IF($G85="待拍板","待定","不开发"))))) -> 二期 | I85: 基础能力随一期APP
A86: 85 | B86: 8 质检溯源 | C86: 质检字段管理 | D86: 质检字段自定义 | E86: 质检字段管理 | F86: 沿用 | G86: P1 | H86: =IF($G86="P0","一期",IF($G86="P1","二期",IF($G86="P2","三期",IF($G86="并行","并行推进",IF($G86="待拍板","待定","不开发"))))) -> 二期
A87: 86 | B87: 8 质检溯源 | C87: 质检模板管理 | D87: 供应商报告＋自检报告两套模板 | E87: 质检模板管理 | F87: 沿用 | G87: P1 | H87: =IF($G87="P0","一期",IF($G87="P1","二期",IF($G87="P2","三期",IF($G87="并行","并行推进",IF($G87="待拍板","待定","不开发"))))) -> 二期
A88: 87 | B88: 8 质检溯源 | C88: 检测报告库 | D88: 报告统一归档备查 | E88: 检测报告（采购侧） | F88: 沿用 | G88: P1 | H88: =IF($G88="P0","一期",IF($G88="P1","二期",IF($G88="P2","三期",IF($G88="并行","并行推进",IF($G88="待拍板","待定","不开发"))))) -> 二期
A89: 88 | B89: 8 质检溯源 | C89: 溯源管理 | D89: 从成品反查原料与批次 | E89: 溯源管理 | F89: 沿用 | G89: P1 | H89: =IF($G89="P0","一期",IF($G89="P1","二期",IF($G89="P2","三期",IF($G89="并行","并行推进",IF($G89="待拍板","待定","不开发"))))) -> 二期
A90: 89 | B90: 8 质检溯源 | C90: 原料/过程/成品质检细分 | D90: 三段质检细分 | E90: 质检管理内 | F90: 沿用 | G90: P1 | H90: =IF($G90="P0","一期",IF($G90="P1","二期",IF($G90="P2","三期",IF($G90="并行","并行推进",IF($G90="待拍板","待定","不开发"))))) -> 二期
A91: 90 | B91: 8 质检溯源 | C91: 不合格处理 | D91: 不合格品处置流程 | E91: — | F91: 新增 | G91: P2 | H91: =IF($G91="P0","一期",IF($G91="P1","二期",IF($G91="P2","三期",IF($G91="并行","并行推进",IF($G91="待拍板","待定","不开发"))))) -> 三期
A92: 91 | B92: 9 分拣配送 | C92: 分拣任务（分解） | D92: 按客户订单分解产出逐项投框 | E92: 分拣进度承接 | F92: 沿用 | G92: P1 | H92: =IF($G92="P0","一期",IF($G92="P1","二期",IF($G92="P2","三期",IF($G92="并行","并行推进",IF($G92="待拍板","待定","不开发"))))) -> 二期 | I92: 分解逻辑核对中（07-06待办）
A93: 92 | B93: 9 分拣配送 | C93: 分拣进度/明细 | D93: 按客户维度跟踪 | E93: 分拣进度/分拣明细（分拣管理） | F93: 沿用 | G93: P1 | H93: =IF($G93="P0","一期",IF($G93="P1","二期",IF($G93="P2","三期",IF($G93="并行","并行推进",IF($G93="待拍板","待定","不开发"))))) -> 二期
A94: 93 | B94: 9 分拣配送 | C94: 投框记录 | D94: 投框与投放记录合并展示 | E94: 投框记录/投放记录（投框管理） | F94: 合并整合 | G94: P1 | H94: =IF($G94="P0","一期",IF($G94="P1","二期",IF($G94="P2","三期",IF($G94="并行","并行推进",IF($G94="待拍板","待定","不开发"))))) -> 二期
A95: 94 | B95: 9 分拣配送 | C95: 筐码管理 | D95: 筐码与客户绑定，可追溯 | E95: 筐码管理（投框管理） | F95: 沿用 | G95: P1 | H95: =IF($G95="P0","一期",IF($G95="P1","二期",IF($G95="P2","三期",IF($G95="并行","并行推进",IF($G95="待拍板","待定","不开发"))))) -> 二期
A96: 95 | B96: 9 分拣配送 | C96: 拣货计划/拣货记录 | D96: 拣货作业 | E96: 拣货计划/拣货记录（拣货管理） | F96: 待确认 | G96: 待拍板 | H96: =IF($G96="P0","一期",IF($G96="P1","二期",IF($G96="P2","三期",IF($G96="并行","并行推进",IF($G96="待拍板","待定","不开发"))))) -> 待定 | I96: Q7：与取货任务/分解取货关系
A97: 96 | B97: 9 分拣配送 | C97: 分拣复核 | D97: 出库前复核 | E97: — | F97: 新增 | G97: P1 | H97: =IF($G97="P0","一期",IF($G97="P1","二期",IF($G97="P2","三期",IF($G97="并行","并行推进",IF($G97="待拍板","待定","不开发"))))) -> 二期
A98: 97 | B98: 9 分拣配送 | C98: 缺货处理 | D98: 分拣缺货登记 | E98: — | F98: 新增 | G98: P2 | H98: =IF($G98="P0","一期",IF($G98="P1","二期",IF($G98="P2","三期",IF($G98="并行","并行推进",IF($G98="待拍板","待定","不开发"))))) -> 三期
A99: 98 | B99: 9 分拣配送 | C99: 配送任务（司机端） | D99: 任务列表，完成一单点掉一单 | E99: 配送任务（配送管理） | F99: 沿用 | G99: P1 | H99: =IF($G99="P0","一期",IF($G99="P1","二期",IF($G99="P2","三期",IF($G99="并行","并行推进",IF($G99="待拍板","待定","不开发"))))) -> 二期 | I99: 简化为基础履约确认
A100: 99 | B100: 9 分拣配送 | C100: 司机管理 | D100: 司机档案与账号 | E100: 司机管理（配送管理） | F100: 沿用 | G100: P1 | H100: =IF($G100="P0","一期",IF($G100="P1","二期",IF($G100="P2","三期",IF($G100="并行","并行推进",IF($G100="待拍板","待定","不开发"))))) -> 二期
...

Sheet 冠麦原始功能去向
A1: 序号 | B1: 冠麦板块 | C1: 冠麦分组 | D1: 冠麦功能项 | E1: 新架构去向 | F1: 处置 | G1: 备注
A2: 1 | B2: 商品 | C2: 商品管理 | D2: 商品列表 | E2: 3 商品/BOM · 商品档案 | F2: 沿用
A3: 2 | B3: 商品 | C3: 商品管理 | D3: 组合商品 | E3: 3 商品/BOM · 组合商品 | F3: 沿用
A4: 3 | B4: 商品 | C4: 商品管理 | D4: 临时商品审批 | E4: — | F4: 裁剪 | G4: 07-06会议
A5: 4 | B5: 商品 | C5: 价格管理 | D5: 客户报价单 | E5: — | F5: 裁剪 | G5: 价格体系整套后置
A6: 5 | B6: 商品 | C6: 价格管理 | D6: 客户协议价 | E6: — | F6: 裁剪
A7: 6 | B7: 商品 | C7: 价格管理 | D7: 历史报价 | E7: — | F7: 裁剪
A8: 7 | B8: 商品 | C8: 商品设置 | D8: 商品分类 | E8: 3 商品/BOM · 商品分类 | F8: 沿用
A9: 8 | B9: 商品 | C9: 商品设置 | D9: 商品税率 | E9: 3 商品/BOM · 商品税率 | F9: 沿用
A10: 9 | B10: 订单 | C10: 订单管理 | D10: 订单列表 | E10: 4 订单中心 · 订单列表/录入/导入 | F10: 沿用
A11: 10 | B11: 订单 | C11: 订单管理 | D11: 预订单 | E11: 4 订单中心 · 预订单 | F11: 待确认 | G11: Q1
A12: 11 | B12: 订单 | C12: 订单管理 | D12: 套账数据 | E12: 4 订单中心 · 套账数据 | F12: 待确认 | G12: Q7 口径待明确
A13: 12 | B13: 订单 | C13: 订单管理 | D13: 菜谱下单 | E13: — | F13: 裁剪
A14: 13 | B14: 订单 | C14: 订单管理 | D14: 未下单客户 | E14: — | F14: 裁剪
A15: 14 | B15: 订单 | C15: 订单管理 | D15: 订单审核 | E15: 4 订单中心 · 订单审核 | F15: 沿用
A16: 15 | B16: 订单 | C16: 订单管理 | D16: 对账审批 | E16: 4 订单中心 · 订单对账→转财务 | F16: 沿用
A17: 16 | B17: 订单 | C17: 售后 | D17: 售后列表 | E17: 4 订单中心 · 售后列表 | F17: 延后 | G17: 暂缓后做
A18: 17 | B18: 订单 | C18: 售后 | D18: 取货任务 | E18: 9 分拣配送 · 拣货 | F18: 待确认 | G18: Q7 与分解取货关系
A19: 18 | B19: 采购 | C19: 采购管理 | D19: 采购计划 | E19: 5 采购中心 · 统一采购单 | F19: 合并整合 | G19: 三合一
A20: 19 | B20: 采购 | C20: 采购管理 | D20: 补采 | E20: 5 · 统一采购单 | F20: 合并整合
A21: 20 | B21: 采购 | C21: 采购管理 | D21: 代采单 | E21: 5 · 代采单 | F21: 待确认 | G21: 会议未提及
A22: 21 | B22: 采购 | C22: 采购管理 | D22: 采购单据 | E22: 5 · 统一采购单 | F22: 合并整合
A23: 22 | B23: 采购 | C23: 采购管理 | D23: 采购员 | E23: 2 基础档案 · 员工档案 | F23: 移位归并 | G23: 角色标识
A24: 23 | B24: 采购 | C24: 采购管理 | D24: 询价记录 | E24: — | F24: 裁剪
A25: 24 | B25: 采购 | C25: 采购管理 | D25: 采购协议价 | E25: — | F25: 裁剪
A26: 25 | B26: 采购 | C26: 采购管理 | D26: 询价单 | E26: — | F26: 裁剪
A27: 26 | B27: 采购 | C27: 采购管理 | D27: 结款审批 | E27: 5 · 结款审批 | F27: 沿用
A28: 27 | B28: 采购 | C28: 采购规则 | D28: 采购计划规则 | E28: — | F28: 裁剪
A29: 28 | B29: 采购 | C29: 采购规则 | D29: 供货比例 | E29: — | F29: 裁剪
A30: 29 | B30: 采购 | C30: 供应商管理 | D30: 供应商信息 | E30: 2 基础档案 · 供应商档案 | F30: 移位归并
A31: 30 | B31: 采购 | C31: 质检管理 | D31: 检测报告 | E31: 5 · 检测报告（联动8质检溯源） | F31: 沿用
A32: 31 | B32: 库存 | C32: 入库管理 | D32: 采购入库单 | E32: 6 库存中心 · 入库单 | F32: 合并整合
A33: 32 | B33: 库存 | C33: 入库管理 | D33: 销售退货入库单 | E33: 6 · 退货类单据 | F33: 延后 | G33: 随售后
A34: 33 | B34: 库存 | C34: 入库管理 | D34: 其他入库单 | E34: 6 · 入库单 | F34: 合并整合
A35: 34 | B35: 库存 | C35: 入库管理 | D35: 其他退货入库单 | E35: 6 · 退货类单据 | F35: 延后
A36: 35 | B36: 库存 | C36: 出库管理 | D36: 采购退货出库单 | E36: 6 · 退货类单据 | F36: 待确认 | G36: 建议P1
A37: 36 | B37: 库存 | C37: 出库管理 | D37: 销售出库单 | E37: 6 · 出库单 | F37: 合并整合
A38: 37 | B38: 库存 | C38: 出库管理 | D38: 其他出库单 | E38: 6 · 出库单 | F38: 合并整合
A39: 38 | B39: 库存 | C39: 出库管理 | D39: 其他退货出库单 | E39: 6 · 退货类单据 | F39: 延后
A40: 39 | B40: 库存 | C40: 盘点管理 | D40: 盘点任务 | E40: 6 · 库存盘点 | F40: 沿用
A41: 40 | B41: 库存 | C41: 盘点管理 | D41: 盘盈单入库单 | E41: 6 · 库存盘点 | F41: 合并整合
A42: 41 | B42: 库存 | C42: 盘点管理 | D42: 盘亏单出库单 | E42: 6 · 库存盘点 | F42: 合并整合
A43: 42 | B43: 库存 | C43: 盘点管理 | D43: 组装拆卸单 | E43: 6 · 组装拆卸单 | F43: 待确认 | G43: 与组合商品联动
A44: 43 | B44: 库存 | C44: 调拨管理 | D44: 调拨任务 | E44: — | F44: 裁剪 | G44: 07-06会议
A45: 44 | B45: 库存 | C45: 调拨管理 | D45: 调拨出库单 | E45: — | F45: 裁剪
A46: 45 | B46: 库存 | C46: 调拨管理 | D46: 调拨入库单 | E46: — | F46: 裁剪
A47: 46 | B47: 库存 | C47: 生产管理 | D47: 领料出库单 | E47: 7 生产中心 · 领料管理 | F47: 沿用
A48: 47 | B48: 库存 | C48: 生产管理 | D48: 生产入库单 | E48: 7 · 产出登记（RK） | F48: 沿用
A49: 48 | B49: 库存 | C49: 生产管理 | D49: 退料入库单 | E49: 7 · 退料管理 | F49: 待确认 | G49: 建议P1
A50: 49 | B50: 库存 | C50: 上下架管理 | D50: 上下架管理 | E50: — | F50: 裁剪 | G50: 仓位类
A51: 50 | B51: 库存 | C51: 上下架管理 | D51: 移库单 | E51: — | F51: 裁剪
A52: 51 | B52: 库存 | C52: 成本管理 | D52: 成本调整单 | E52: 11 财务中心 · 成本核算 | F52: 待确认 | G52: Q4
A53: 52 | B53: 库存 | C53: 成本管理 | D53: 成本核算 | E53: 11 · 成本核算 | F53: 待确认 | G53: Q4
A54: 53 | B54: 库存 | C54: 库存数据 | D54: 库存查询表 | E54: 6 · 库存查询 | F54: 沿用
A55: 54 | B55: 库存 | C55: 库存数据 | D55: 在途库存分布 | E55: — | F55: 裁剪 | G55: 07-06会议
A56: 55 | B56: 库存 | C56: 库存数据 | D56: 占用库存分布 | E56: — | F56: 延后 | G56: 会议未提
A57: 56 | B57: 库存 | C57: 库存数据 | D57: 待出库数据分布 | E57: — | F57: 延后
A58: 57 | B58: 库存 | C58: 库存数据 | D58: 出入库明细 | E58: 6 · 库存查询 | F58: 沿用
A59: 58 | B59: 库存 | C59: 库存报表 | D59: 台账汇总 | E59: 12 报表中心 · 仓储报表 | F59: 延后 | G59: P2
A60: 59 | B60: 库存 | C60: 库存报表 | D60: 台账明细 | E60: 12 · 仓储报表 | F60: 延后
A61: 60 | B61: 库存 | C61: 库存报表 | D61: 原始台账明细 | E61: 12 · 仓储报表 | F61: 延后
A62: 61 | B62: 库存 | C62: 库存报表 | D62: 采购出入库汇总 | E62: 12 · 仓储报表 | F62: 延后
A63: 62 | B63: 库存 | C63: 库存报表 | D63: 库存日报 | E63: 12 · 仓储报表 | F63: 延后
A64: 63 | B64: 库存 | C64: 库存报表 | D64: 库存商品日报 | E64: 12 · 仓储报表 | F64: 延后
A65: 64 | B65: 库存 | C65: 对账单 | D65: 供应商对账 | E65: 11 财务中心 · 供应商结算 | F65: 移位归并 | G65: 会议明确归财务
A66: 65 | B66: 库存 | C66: 对账单 | D66: 费用单 | E66: 11 · 费用单/收入单 | F66: 待确认 | G66: 会议未提
A67: 66 | B67: 库存 | C67: 对账单 | D67: 收入单 | E67: 11 · 费用单/收入单 | F67: 待确认
A68: 67 | B68: 生产 | C68: 生产管理 | D68: 生产计划 | E68: 7 生产中心 · 生产计划 | F68: 沿用 | G68: 去餐次
A69: 68 | B69: 生产 | C69: 生产管理 | D69: 领料管理 | E69: 7 · 领料管理 | F69: 沿用
A70: 69 | B70: 生产 | C70: 生产管理 | D70: 生产进度 | E70: 7 · 工序报工 | F70: 沿用 | G70: 新架构增强为开工/报工留痕
A71: 70 | B71: 生产 | C71: 生产管理 | D71: 投料与产出记录 | E71: 7 · 投料登记/产出登记 | F71: 沿用
A72: 71 | B72: 生产 | C72: 生产管理 | D72: 退料管理 | E72: 7 · 退料管理 | F72: 待确认 | G72: 建议P1
A73: 72 | B73: 生产 | C73: 生产管理 | D73: 产出管理 | E73: 7 · 产出登记 | F73: 沿用
A74: 73 | B74: 生产 | C74: 生产管理 | D74: 线边仓库存总览 | E74: 7 · 线边仓库存总览 | F74: 沿用 | G74: 只读P1
A75: 74 | B75: 生产 | C75: 生产管理 | D75: 商品台账 | E75: 12 报表中心 | F75: 延后
A76: 75 | B76: 生产 | C76: BOM管理 | D76: 生产BOM管理 | E76: 3 商品/BOM · 生产BOM维护 | F76: 移位归并
A77: 76 | B77: 生产 | C77: BOM管理 | D77: 研发BOM管理 | E77: 3 · 研发BOM | F77: 待确认 | G77: 会议未提
A78: 77 | B78: 生产 | C78: 生产设置 | D78: 工厂模型 | E78: 2 基础档案 · 组织管理 | F78: 移位归并
A79: 78 | B79: 生产 | C79: 生产设置 | D79: 工序管理 | E79: 7 · 工序管理 | F79: 沿用
A80: 79 | B80: 生产 | C80: 生产设置 | D80: 商品内标管理 | E80: 3 · 商品内标管理 | F80: 待确认 | G80: 会议未提
A81: 80 | B81: 生产 | C81: 生产设置 | D81: 替代商品 | E81: — | F81: 裁剪 | G81: 07-06会议
A82: 81 | B82: 生产 | C82: 生产工具 | D82: 打印箱签 | E82: 7 · 打印箱签 | F82: 待确认 | G82: 建议P1保留
A83: 82 | B83: 质检 | C83: 质检管理 | D83: 质检管理 | E83: 8 质检溯源 · 质检管理 | F83: 沿用
A84: 83 | B84: 质检 | C84: 质检管理 | D84: 质检字段管理 | E84: 8 · 质检字段管理 | F84: 沿用
A85: 84 | B85: 质检 | C85: 质检管理 | D85: 质检模板管理 | E85: 8 · 质检模板管理 | F85: 沿用
A86: 85 | B86: 质检 | C86: 溯源管理 | D86: 溯源管理 | E86: 8 · 溯源管理 | F86: 沿用
A87: 86 | B87: 分拣 | C87: 分拣管理 | D87: 分拣进度 | E87: 9 分拣配送 · 分拣进度 | F87: 沿用
A88: 87 | B88: 分拣 | C88: 分拣管理 | D88: 分拣明细 | E88: 9 · 分拣明细 | F88: 沿用
A89: 88 | B89: 分拣 | C89: 投框管理 | D89: 筐码管理 | E89: 9 · 筐码管理 | F89: 沿用
A90: 89 | B90: 分拣 | C90: 投框管理 | D90: 投框记录 | E90: 9 · 投框记录 | F90: 沿用
A91: 90 | B91: 分拣 | C91: 投框管理 | D91: 投放记录 | E91: 9 · 投框记录 | F91: 合并整合
A92: 91 | B92: 分拣 | C92: 拣货管理 | D92: 拣货计划 | E92: 9 · 拣货计划/记录 | F92: 待确认 | G92: Q7
A93: 92 | B93: 分拣 | C93: 拣货管理 | D93: 拣货记录 | E93: 9 · 拣货计划/记录 | F93: 待确认 | G93: Q7
A94: 93 | B94: 配送 | C94: 配送管理 | D94: 配送任务 | E94: 9 · 配送任务（司机端） | F94: 沿用 | G94: 简化履约确认
A95: 94 | B95: 配送 | C95: 配送管理 | D95: 司机管理 | E95: 9 · 司机管理 | F95: 沿用
A96: 95 | B96: 配送 | C96: 配送管理 | D96: 线路管理 | E96: — | F96: 裁剪 | G96: 07-06会议
A97: 96 | B97: 配送 | C97: 配送进度 | D97: 调度中心 | E97: — | F97: 裁剪 | G97: 复杂调度
A98: 97 | B98: 财务 | C98: 客户结算 | D98: 客户账单 | E98: 11 财务中心 · 客户结算 | F98: 沿用
A99: 98 | B99: 财务 | C99: 客户结算 | D99: 客户结款 | E99: 11 · 客户结算 | F99: 沿用
A100: 99 | B100: 财务 | C100: 客户结算 | D100: 结款凭证 | E100: 11 · 结款凭证 | F100: 沿用
...

Sheet 汇总
A1: 一级模块 | B1: P0 | C1: P1 | D1: P2 | E1: 并行 | F1: 待拍板 | G1: 裁剪 | H1: 功能合计 | I1: 开发范围小计
A2: 1 工作台 | B2: =COUNTIFS('功能清单（新架构）'!$B:$B,$A2,'功能清单（新架构）'!$G:$G,B$1) -> 5 | C2: =COUNTIFS('功能清单（新架构）'!$B:$B,$A2,'功能清单（新架构）'!$G:$G,C$1) -> 1 | D2: =COUNTIFS('功能清单（新架构）'!$B:$B,$A2,'功能清单（新架构）'!$G:$G,D$1) -> 0 | E2: =COUNTIFS('功能清单（新架构）'!$B:$B,$A2,'功能清单（新架构）'!$G:$G,E$1) -> 0 | F2: =COUNTIFS('功能清单（新架构）'!$B:$B,$A2,'功能清单（新架构）'!$G:$G,F$1) -> 0 | G2: =COUNTIFS('功能清单（新架构）'!$B:$B,$A2,'功能清单（新架构）'!$G:$G,G$1) -> 0 | H2: =SUM(B2:G2) -> 6 | I2: =H2-G2 -> 6
A3: 2 基础档案 | B3: =COUNTIFS('功能清单（新架构）'!$B:$B,$A3,'功能清单（新架构）'!$G:$G,B$1) -> 9 | C3: =COUNTIFS('功能清单（新架构）'!$B:$B,$A3,'功能清单（新架构）'!$G:$G,C$1) -> 2 | D3: =COUNTIFS('功能清单（新架构）'!$B:$B,$A3,'功能清单（新架构）'!$G:$G,D$1) -> 0 | E3: =COUNTIFS('功能清单（新架构）'!$B:$B,$A3,'功能清单（新架构）'!$G:$G,E$1) -> 0 | F3: =COUNTIFS('功能清单（新架构）'!$B:$B,$A3,'功能清单（新架构）'!$G:$G,F$1) -> 0 | G3: =COUNTIFS('功能清单（新架构）'!$B:$B,$A3,'功能清单（新架构）'!$G:$G,G$1) -> 0 | H3: =SUM(B3:G3) -> 11 | I3: =H3-G3 -> 11
A4: 3 商品/BOM | B4: =COUNTIFS('功能清单（新架构）'!$B:$B,$A4,'功能清单（新架构）'!$G:$G,B$1) -> 7 | C4: =COUNTIFS('功能清单（新架构）'!$B:$B,$A4,'功能清单（新架构）'!$G:$G,C$1) -> 1 | D4: =COUNTIFS('功能清单（新架构）'!$B:$B,$A4,'功能清单（新架构）'!$G:$G,D$1) -> 0 | E4: =COUNTIFS('功能清单（新架构）'!$B:$B,$A4,'功能清单（新架构）'!$G:$G,E$1) -> 0 | F4: =COUNTIFS('功能清单（新架构）'!$B:$B,$A4,'功能清单（新架构）'!$G:$G,F$1) -> 2 | G4: =COUNTIFS('功能清单（新架构）'!$B:$B,$A4,'功能清单（新架构）'!$G:$G,G$1) -> 3 | H4: =SUM(B4:G4) -> 13 | I4: =H4-G4 -> 10
A5: 4 订单中心 | B5: =COUNTIFS('功能清单（新架构）'!$B:$B,$A5,'功能清单（新架构）'!$G:$G,B$1) -> 5 | C5: =COUNTIFS('功能清单（新架构）'!$B:$B,$A5,'功能清单（新架构）'!$G:$G,C$1) -> 2 | D5: =COUNTIFS('功能清单（新架构）'!$B:$B,$A5,'功能清单（新架构）'!$G:$G,D$1) -> 1 | E5: =COUNTIFS('功能清单（新架构）'!$B:$B,$A5,'功能清单（新架构）'!$G:$G,E$1) -> 0 | F5: =COUNTIFS('功能清单（新架构）'!$B:$B,$A5,'功能清单（新架构）'!$G:$G,F$1) -> 2 | G5: =COUNTIFS('功能清单（新架构）'!$B:$B,$A5,'功能清单（新架构）'!$G:$G,G$1) -> 3 | H5: =SUM(B5:G5) -> 13 | I5: =H5-G5 -> 10
A6: 5 采购中心 | B6: =COUNTIFS('功能清单（新架构）'!$B:$B,$A6,'功能清单（新架构）'!$G:$G,B$1) -> 0 | C6: =COUNTIFS('功能清单（新架构）'!$B:$B,$A6,'功能清单（新架构）'!$G:$G,C$1) -> 5 | D6: =COUNTIFS('功能清单（新架构）'!$B:$B,$A6,'功能清单（新架构）'!$G:$G,D$1) -> 0 | E6: =COUNTIFS('功能清单（新架构）'!$B:$B,$A6,'功能清单（新架构）'!$G:$G,E$1) -> 0 | F6: =COUNTIFS('功能清单（新架构）'!$B:$B,$A6,'功能清单（新架构）'!$G:$G,F$1) -> 1 | G6: =COUNTIFS('功能清单（新架构）'!$B:$B,$A6,'功能清单（新架构）'!$G:$G,G$1) -> 2 | H6: =SUM(B6:G6) -> 8 | I6: =H6-G6 -> 6
A7: 6 库存中心 | B7: =COUNTIFS('功能清单（新架构）'!$B:$B,$A7,'功能清单（新架构）'!$G:$G,B$1) -> 0 | C7: =COUNTIFS('功能清单（新架构）'!$B:$B,$A7,'功能清单（新架构）'!$G:$G,C$1) -> 4 | D7: =COUNTIFS('功能清单（新架构）'!$B:$B,$A7,'功能清单（新架构）'!$G:$G,D$1) -> 3 | E7: =COUNTIFS('功能清单（新架构）'!$B:$B,$A7,'功能清单（新架构）'!$G:$G,E$1) -> 0 | F7: =COUNTIFS('功能清单（新架构）'!$B:$B,$A7,'功能清单（新架构）'!$G:$G,F$1) -> 3 | G7: =COUNTIFS('功能清单（新架构）'!$B:$B,$A7,'功能清单（新架构）'!$G:$G,G$1) -> 3 | H7: =SUM(B7:G7) -> 13 | I7: =H7-G7 -> 10
A8: 7 生产中心 | B8: =COUNTIFS('功能清单（新架构）'!$B:$B,$A8,'功能清单（新架构）'!$G:$G,B$1) -> 10 | C8: =COUNTIFS('功能清单（新架构）'!$B:$B,$A8,'功能清单（新架构）'!$G:$G,C$1) -> 3 | D8: =COUNTIFS('功能清单（新架构）'!$B:$B,$A8,'功能清单（新架构）'!$G:$G,D$1) -> 1 | E8: =COUNTIFS('功能清单（新架构）'!$B:$B,$A8,'功能清单（新架构）'!$G:$G,E$1) -> 0 | F8: =COUNTIFS('功能清单（新架构）'!$B:$B,$A8,'功能清单（新架构）'!$G:$G,F$1) -> 2 | G8: =COUNTIFS('功能清单（新架构）'!$B:$B,$A8,'功能清单（新架构）'!$G:$G,G$1) -> 3 | H8: =SUM(B8:G8) -> 19 | I8: =H8-G8 -> 16
A9: 8 质检溯源 | B9: =COUNTIFS('功能清单（新架构）'!$B:$B,$A9,'功能清单（新架构）'!$G:$G,B$1) -> 0 | C9: =COUNTIFS('功能清单（新架构）'!$B:$B,$A9,'功能清单（新架构）'!$G:$G,C$1) -> 6 | D9: =COUNTIFS('功能清单（新架构）'!$B:$B,$A9,'功能清单（新架构）'!$G:$G,D$1) -> 1 | E9: =COUNTIFS('功能清单（新架构）'!$B:$B,$A9,'功能清单（新架构）'!$G:$G,E$1) -> 0 | F9: =COUNTIFS('功能清单（新架构）'!$B:$B,$A9,'功能清单（新架构）'!$G:$G,F$1) -> 0 | G9: =COUNTIFS('功能清单（新架构）'!$B:$B,$A9,'功能清单（新架构）'!$G:$G,G$1) -> 0 | H9: =SUM(B9:G9) -> 7 | I9: =H9-G9 -> 7
A10: 9 分拣配送 | B10: =COUNTIFS('功能清单（新架构）'!$B:$B,$A10,'功能清单（新架构）'!$G:$G,B$1) -> 0 | C10: =COUNTIFS('功能清单（新架构）'!$B:$B,$A10,'功能清单（新架构）'!$G:$G,C$1) -> 8 | D10: =COUNTIFS('功能清单（新架构）'!$B:$B,$A10,'功能清单（新架构）'!$G:$G,D$1) -> 2 | E10: =COUNTIFS('功能清单（新架构）'!$B:$B,$A10,'功能清单（新架构）'!$G:$G,E$1) -> 0 | F10: =COUNTIFS('功能清单（新架构）'!$B:$B,$A10,'功能清单（新架构）'!$G:$G,F$1) -> 1 | G10: =COUNTIFS('功能清单（新架构）'!$B:$B,$A10,'功能清单（新架构）'!$G:$G,G$1) -> 2 | H10: =SUM(B10:G10) -> 13 | I10: =H10-G10 -> 11
A11: 10 客户中心 | B11: =COUNTIFS('功能清单（新架构）'!$B:$B,$A11,'功能清单（新架构）'!$G:$G,B$1) -> 3 | C11: =COUNTIFS('功能清单（新架构）'!$B:$B,$A11,'功能清单（新架构）'!$G:$G,C$1) -> 2 | D11: =COUNTIFS('功能清单（新架构）'!$B:$B,$A11,'功能清单（新架构）'!$G:$G,D$1) -> 0 | E11: =COUNTIFS('功能清单（新架构）'!$B:$B,$A11,'功能清单（新架构）'!$G:$G,E$1) -> 0 | F11: =COUNTIFS('功能清单（新架构）'!$B:$B,$A11,'功能清单（新架构）'!$G:$G,F$1) -> 0 | G11: =COUNTIFS('功能清单（新架构）'!$B:$B,$A11,'功能清单（新架构）'!$G:$G,G$1) -> 2 | H11: =SUM(B11:G11) -> 7 | I11: =H11-G11 -> 5
A12: 11 财务中心 | B12: =COUNTIFS('功能清单（新架构）'!$B:$B,$A12,'功能清单（新架构）'!$G:$G,B$1) -> 0 | C12: =COUNTIFS('功能清单（新架构）'!$B:$B,$A12,'功能清单（新架构）'!$G:$G,C$1) -> 3 | D12: =COUNTIFS('功能清单（新架构）'!$B:$B,$A12,'功能清单（新架构）'!$G:$G,D$1) -> 2 | E12: =COUNTIFS('功能清单（新架构）'!$B:$B,$A12,'功能清单（新架构）'!$G:$G,E$1) -> 0 | F12: =COUNTIFS('功能清单（新架构）'!$B:$B,$A12,'功能清单（新架构）'!$G:$G,F$1) -> 3 | G12: =COUNTIFS('功能清单（新架构）'!$B:$B,$A12,'功能清单（新架构）'!$G:$G,G$1) -> 1 | H12: =SUM(B12:G12) -> 9 | I12: =H12-G12 -> 8
A13: 12 报表中心 | B13: =COUNTIFS('功能清单（新架构）'!$B:$B,$A13,'功能清单（新架构）'!$G:$G,B$1) -> 0 | C13: =COUNTIFS('功能清单（新架构）'!$B:$B,$A13,'功能清单（新架构）'!$G:$G,C$1) -> 0 | D13: =COUNTIFS('功能清单（新架构）'!$B:$B,$A13,'功能清单（新架构）'!$G:$G,D$1) -> 8 | E13: =COUNTIFS('功能清单（新架构）'!$B:$B,$A13,'功能清单（新架构）'!$G:$G,E$1) -> 0 | F13: =COUNTIFS('功能清单（新架构）'!$B:$B,$A13,'功能清单（新架构）'!$G:$G,F$1) -> 1 | G13: =COUNTIFS('功能清单（新架构）'!$B:$B,$A13,'功能清单（新架构）'!$G:$G,G$1) -> 1 | H13: =SUM(B13:G13) -> 10 | I13: =H13-G13 -> 9
... A15: 14 应用市场 | B15: =COUNTIFS('功能清单（新架构）'!$B:$B,$A15,'功能清单（新架构）'!$G:$G,B$1) -> 0 | C15: =COUNTIFS('功能清单（新架构）'!$B:$B,$A15,'功能清单（新架构）'!$G:$G,C$1) -> 0 | D15: =COUNTIFS('功能清单（新架构）'!$B:$B,$A15,'功能清单（新架构）'!$G:$G,D$1) -> 3 | E15: =COUNTIFS('功能清单（新架构）'!$B:$B,$A15,'功能清单（新架构）'!$G:$G,E$1) -> 2 | F15: =COUNTIFS('功能清单（新架构）'!$B:$B,$A15,'功能清单（新架构）'!$G:$G,F$1) -> 0 | G15: =COUNTIFS('功能清单（新架构）'!$B:$B,$A15,'功能清单（新架构）'!$G:$G,G$1) -> 0 | H15: =SUM(B15:G15) -> 5 | I15: =H15-G15 -> 5
A16: 合计 | B16: =SUM(B2:B15) -> 39 | C16: =SUM(C2:C15) -> 37 | D16: =SUM(D2:D15) -> 29 | E16: =SUM(E2:E15) -> 2 | F16: =SUM(F2:F15) -> 15 | G16: =SUM(G2:G15) -> 20 | H16: =SUM(H2:H15) -> 142 | I16: =SUM(I2:I15) -> 122
A18: 冠麦功能处置统计（共 121 项，来自10张截图）
B19: 沿用 | C19: 合并整合 | D19: 移位归并 | E19: 裁剪 | F19: 延后 | G19: 待确认 | H19: 合计
B20: =COUNTIF(冠麦原始功能去向!$F:$F,B19) -> 35 | C20: =COUNTIF(冠麦原始功能去向!$F:$F,C19) -> 10 | D20: =COUNTIF(冠麦原始功能去向!$F:$F,D19) -> 5 | E20: =COUNTIF(冠麦原始功能去向!$F:$F,E19) -> 20 | F20: =COUNTIF(冠麦原始功能去向!$F:$F,F19) -> 30 | G20: =COUNTIF(冠麦原始功能去向!$F:$F,G19) -> 21 | H20: =SUM(B20:G20) -> 121
A22: 处置定义：沿用=直接保留｜合并整合=多项合一｜移位归并=换模块归属｜裁剪=07-06会议已定不做｜延后=P2后置｜待确认=会议未提或口径矛盾，进拍板清单
A23: 本版新发现待拍板项（冠麦有、会议未提）：代采单、组装拆卸单、退料管理、研发BOM、商品内标、打印箱签、拣货计划/记录、费用单/收入单、流水提现、项目点报表、占用/待出库分布、退货类单据
A24: 冠麦截图缺失板块：基础档案/系统设置、权限、客户——对照待补，相关行标注“截图未提供”
A25: 口径来源：07-06会议纪要、PRD v0.9、冠麦系统截图（2026-07-09提供）；Q编号见PRD第7章与《第一次产品讨论包》
